fastpy_rs-0.1.1.dist-info/METADATA
fastpy_rs-0.1.1.dist-info/WHEEL
fastpy_rs/__init__.py
fastpy_rs/fastpy_rs.cp313-win_amd64.pyd
fastpy_rs-0.1.1.dist-info/RECORD
