Metadata-Version: 2.4
Name: fastpy_rs
Version: 0.1.1
Summary: 
Keywords: rust,python,pyo3,maturin
Home-Page: https://github.com/evgenyigumnov/fastpy-rs
Author: Evgeny Igumnov <igumnovnsk@gmail.com>
Author-email: Evgeny Igumnov <igumnovnsk@gmail.com>
License: MIT
Project-URL: Source Code, https://github.com/evgenyigumnov/fastpy-rs
